MotifDiff/MotifDiff.py
MotifDiff/__init__.py
MotifDiff/util.py
MotifDiff-1.2.dist-info/METADATA
MotifDiff-1.2.dist-info/WHEEL
MotifDiff-1.2.dist-info/entry_points.txt
MotifDiff-1.2.dist-info/top_level.txt
MotifDiff-1.2.dist-info/RECORD
